{
  "games": [
    {
      "id": 1,
      "name": "The Last of Us",
      "price": 2000
    },
    {
      "id": 2,
      "name": "GTA V",
      "price": 600
    },
    {
      "id": 4,
      "name": "Stray",
      "price": 59.9
    },
    {
      "name": "Spiderman",
      "price": 100,
      "id": 6
    },
    {
      "name": "Miles Morales",
      "price": "200",
      "id": 7
    },
    {
      "name": "Days Gone",
      "price": "40",
      "id": 9
    },
    {
      "name": "dadads",
      "price": 23,
      "id": 10
    }
  ]
}